Workbook
Name adspend: 'Sales Data'!$Y$3:$Y$1001
Name bankcomission: 'Sales Data'!$R$2:$R$1001
Name bankcommisionamount: 'Sales Data'!$S$2:$S$1001
Name category: 'Sales Data'!$J$2:$J$1001
Name City: 'Sales Data'!$H$2:$H$1001
Name Course: 'Sales Data'!$I$2:$I$1001
Name Customerid: 'Sales Data'!$E$2:$E$1001
Name customertype: 'Sales Data'!$F$2:$F$1001
Name discountamount: 'Sales Data'!$N$2:$N$1001
Name expected: 'Sales Data'!$L$932
Name expectedrevenue: 'Sales Data'!$Q$2:$Q$1001
Name finalpaidamount: 'Sales Data'!$O$2:$O$1001
Name gender: 'Sales Data'!$G$2:$G$1001
Name incometax: 'Sales Data'!$T$2:$T$1001
Name incometaxamount: 'Sales Data'!$U$2:$U$1001
Name marketingchannel: 'Sales Data'!$X$3:$X$1001
Name netrevenue: 'Sales Data'!$W$3:$W$1001
Name orderdate: 'Sales Data'!$B$2:$B$1001
Name originalprice: 'Sales Data'!$K$2:$K$1001
Name paymentdate: 'Sales Data'!$C$2:$C$1001
Name PAYMENTm: 'Sales Data'!$D$2:$D$1001
Name paymentmethod: 'Sales Data'!$M$2:$M$1001
Name paymentstatus: 'Sales Data'!$L$2:$L$1001
Name refundamount: 'Sales Data'!$V$2:$V$1001
Name Slicer_Category: #N/A
Name Slicer_City: #N/A
Name Slicer_Course: #N/A
Name Slicer_Marketing_Channel: #N/A
Name Slicer_Payment_Status: #N/A
Name totalsales: 'Sales Data'!$P$2:$P$1001

Sheet Data Dictionary
A7: Column Name | C7: Description
A8: Sales ID | C8: Unique identifier for each sales transaction
A9: Order Date | C9: Date when the customer placed the order
A10: Payment Date | C10: Date when the payment was completed
A11: Customer ID | C11: Unique identifier for each customer
A12: Customer Type | C12: Type of customer (New customer, Returning customer, etc.)
A13: Gender | C13: Customer gender information
A14: City | C14: Customer location
A15: Course | C15: Name of the purchased course
A16: Category | C16: Category of the purchased course
A17: Original Price | C17: Course price before applying discounts
A18: Payment Status | C18: Current payment status (Paid, Pending, Refunded)
... A30: Ad Spend | C30: Amount spent on advertising campaigns

Sheet Pivots
A3: Sum of Total Sales | B3: Sum of Net Revenue | C3: Sum of Expected Revenue | D3: Sum of Refund Amount | E3: Sum of Refund Amount | G3: Row Labels | H3: Sum of Net Revenue | J3: Count of Customer ID | K3: Column Labels
A4: 34764.355 | B4: 20086.481 | C4: 11193.674 | D4: 3138.3148 | E4: 3138.3148 | G4: Data Analytics | H4: 9455.7226 | J4: Row Labels | K4: Female | L4: Male | M4: Not specified | N4: Grand Total
G5: Finance & Taxation | H5: 2126.416 | J5: January | K5: 54 | L5: 51 | M5: 47 | N5: 152
A6: =GETPIVOTDATA("Total Sales",$A$3) -> 34764.355 | B6: =GETPIVOTDATA("Net Revenue",$B$3) -> 20086.481 | C6: =GETPIVOTDATA("Expected Revenue",$C$3) -> 11193.674 | D6: =GETPIVOTDATA("Refund Amount",$D$3) -> 3138.3148 | E6: =GETPIVOTDATA("Refund Amount",$E$3) -> 3138.3148 | G6: Microsoft Office | H6: 5753.2068 | J6: February | K6: 47 | L6: 40 | M6: 41 | N6: 128
G7: Psychology | H7: 2751.1357 | J7: March | K7: 48 | L7: 51 | M7: 46 | N7: 145
G8: Grand Total | H8: 20086.481 | J8: April | K8: 52 | L8: 44 | M8: 45 | N8: 141
J9: May | K9: 52 | L9: 44 | M9: 50 | N9: 146
A10: Sum of Total Sales | J10: June | K10: 45 | L10: 43 | M10: 44 | N10: 132
A11: 34764.355 | J11: July | K11: 51 | L11: 52 | M11: 53 | N11: 156
J12: Grand Total | K12: 349 | L12: 325 | M12: 326 | N12: 1000
A14: Sum of Final Paid Amount
A15: 35570
J17: Count of Sales ID
A18: Row Labels | B18: Sum of Net Revenue | D18: Row Labels | E18: Sum of Net Revenue | J18: 1000
A19: January | B19: 24.1758 | D19: SQL | E19: 6710.7447 | G19: Row Labels | H19: Sum of Net Revenue | I19: Sum of Ad Spend
A20: February | B20: 4288.0464 | D20: Adolescent Psychology | E20: 2751.1357 | G20: Facebook | H20: 7113.1104 | I20: 640
A21: March | B21: -116.8992 | D21: Power BI | E21: 2744.9779 | G21: Instagram | H21: 5839.4853 | I21: 690
A22: April | B22: 4753.2177 | D22: Tax Code | E22: 2126.416 | G22: Tiktok | H22: 7133.8855 | I22: 770
A23: May | B23: 3602.7189 | D23: PowerPoint | E23: 1825.956 | G23: Grand Total | H23: 20086.481 | I23: 2100
A24: June | B24: 3552.115 | D24: Complete Excel Course | E24: 1702.9435
A25: July | B25: 3983.1066 | D25: Microsoft Word | E25: 1327.694
A26: Grand Total | B26: 20086.481 | D26: Excel Basics | E26: 896.6133
D27: Grand Total | E27: 20086.481 | G27: Row Labels | H27: Count of Sales ID
G28: Paid | H28: 607
A29: Row Labels | B29: Sum of Expected Revenue | D29: Row Labels | E29: Sum of Refund Amount | G29: Pending | H29: 292
A30: January | B30: 1714.3682 | D30: January | E30: 135.19935 | G30: Refunded | H30: 101
A31: February | B31: 1786.0441 | D31: February | E31: 254.57355 | G31: Grand Total | H31: 1000
A32: March | B32: -493.3903 | D32: March | E32: -410.49855
A33: April | B33: 1389.6284 | D33: April | E33: 852.57315 | G33: Row Labels | H33: Count of Sales ID
A34: May | B34: 2826.2718 | D34: May | E34: 492.1092 | G34: Bank Transfer | H34: 177
A35: June | B35: 1688.6331 | D35: June | E35: 1027.9814 | G35: Mastercard Credit | H35: 203
A36: July | B36: 2282.1183 | D36: July | E36: 786.3768 | G36: Mastercard Debit | H36: 221
A37: Grand Total | B37: 11193.674 | D37: Grand Total | E37: 3138.3148 | G37: Visa Credit | H37: 200
G38: Visa Debit | H38: 199
G39: Grand Total | H39: 1000

Sheet Sales Data
A1: Sales ID | B1: Order Date | C1: Payment Date | D1: Month | E1: Customer ID | F1: Customer Type | G1: Gender | H1: City | I1: Course | J1: Category | K1: Original Price | L1: Payment Status | M1: Payment Method | N1: Discount Amount | O1: Final Paid Amount | P1: Total Sales | Q1: Expected Revenue | R1: Bank Commission % | S1: Bank Commision Amount | T1: Income Tax % | U1: Income Tax amount | V1: Refund Amount | W1: Net Revenue | X1: Marketing Channel | Y1: Ad Spend
A2: 1 | B2: 46081 | C2: 46085 | D2: =TEXT(C2,"mmmm") -> March | E2: ="STU-"&RANDBETWEEN(1,1000) -> STU-859 | F2: =IF(COUNTIF($E$2:E2,E2)=1,"New Customer","Returning Customer") -> New Customer | G2: =CHOOSE(RANDBETWEEN(1,3),"Male","Female","Not specified") -> Male | H2: Gori | I2: {=INDEX(Courses!$B$9:$B$16,RANDBETWEEN(1,8))} -> Tax Code | J2: =VLOOKUP(I2,Courses!$B$9:$C$16,2,0) -> Finance & Taxation | K2: =VLOOKUP(I2,Courses!$B$9:$D$16,3,0) -> 59 | L2: =IF(RAND()<0.6,"Paid",IF(RAND()<0.75,"Pending","Refunded")) -> Pending | M2: {=INDEX('Payment Method'!$A$8:$A$12,RANDBETWEEN(1,5))} -> Bank Transfer | N2: =IFERROR(SUMIF(Holiday!$A$8:$A$11,B2,Holiday!$C$8:$C$11),0) -> 0 | O2: =K2-K2*N2 -> 59 | P2: =O2-S2 -> 59 | Q2: =IF(L2="pending",K2-N2,0) -> 59 | R2: =VLOOKUP(M2,'Payment Method'!$A$8:$B$12,2,0) -> 0 | S2: =O2-(O2-O2*R2) -> 0 | T2: 0.01 | U2: =O2-S2-((O2-S2)-(O2-S2)*T2) -> 0.59 | V2: =IF(L2="refunded",(K2-K2*N2)-(K2-K2*N2)*R2-((K2-K2*N2)-(K2-K2*N2)*R2)*T2,0) -> 0 | W2: =IF(L2="paid",(K2-K2*N2)-(K2-K2*N2)*R2-((K2-K2*N2)-(K2-K2*N2)*R2)*T2,0) -> 0 | X2: =CHOOSE(RANDBETWEEN(1,3),"Facebook","Instagram","Tiktok") -> Instagram | Y2: =IF(COUNTIF($C$1:C1,B1)=1,10,"")
A3: 2 | B3: 46198 | C3: 46202 | D3: =TEXT(C3,"mmmm") -> June | E3: ="STU-"&RANDBETWEEN(1,1000) -> STU-494 | F3: =IF(COUNTIF($E$2:E3,E3)=1,"New Customer","Returning Customer") -> New Customer | G3: =CHOOSE(RANDBETWEEN(1,3),"Male","Female","Not specified") -> Not specified | H3: Batumi | I3: {=INDEX(Courses!$B$9:$B$16,RANDBETWEEN(1,8))} -> Excel Basics | J3: =VLOOKUP(I3,Courses!$B$9:$C$16,2,0) -> Microsoft Office | K3: =VLOOKUP(I3,Courses!$B$9:$D$16,3,0) -> 29 | L3: =IF(RAND()<0.6,"Paid",IF(RAND()<0.75,"Pending","Refunded")) -> Paid | M3: {=INDEX('Payment Method'!$A$8:$A$12,RANDBETWEEN(1,5))} -> Visa Credit | N3: =IFERROR(SUMIF(Holiday!$A$8:$A$11,B3,Holiday!$C$8:$C$11),0) -> 0 | O3: =K3-K3*N3 -> 29 | P3: =O3-S3 -> 27.985 | Q3: =IF(L3="pending",(K3-K3*N3)-(K3-K3*N3)*R3-((K3-K3*N3)-(K3-K3*N3)*R3)*T3,0) -> 0 | R3: =VLOOKUP(M3,'Payment Method'!$A$8:$B$12,2,0) -> 0.035 | S3: =O3-(O3-O3*R3) -> 1.015 | T3: 0.01 | U3: =O3-S3-((O3-S3)-(O3-S3)*T3) -> 0.27985 | V3: =IF(L3="refunded",(K3-K3*N3)-(K3-K3*N3)*R3-((K3-K3*N3)-(K3-K3*N3)*R3)*T3,0) -> 0 | W3: =IF(L3="paid",(K3-K3*N3)-(K3-K3*N3)*R3-((K3-K3*N3)-(K3-K3*N3)*R3)*T3,0) -> 27.70515 | X3: =CHOOSE(RANDBETWEEN(1,3),"Facebook","Instagram","Tiktok") -> Tiktok | Y3: =IF(COUNTIF($C$1:C2,B2)=1,10,"")
A4: 3 | B4: 46233 | C4: 46233 | D4: =TEXT(C4,"mmmm") -> July | E4: ="STU-"&RANDBETWEEN(1,1000) -> STU-296 | F4: =IF(COUNTIF($E$2:E4,E4)=1,"New Customer","Returning Customer") -> New Customer | G4: =CHOOSE(RANDBETWEEN(1,3),"Male","Female","Not specified") -> Male | H4: Kutaisi | I4: {=INDEX(Courses!$B$9:$B$16,RANDBETWEEN(1,8))} -> Tax Code | J4: =VLOOKUP(I4,Courses!$B$9:$C$16,2,0) -> Finance & Taxation | K4: =VLOOKUP(I4,Courses!$B$9:$D$16,3,0) -> 59 | L4: =IF(RAND()<0.6,"Paid",IF(RAND()<0.75,"Pending","Refunded")) -> Pending | M4: {=INDEX('Payment Method'!$A$8:$A$12,RANDBETWEEN(1,5))} -> Mastercard Credit | N4: =IFERROR(SUMIF(Holiday!$A$8:$A$11,B4,Holiday!$C$8:$C$11),0) -> 0 | O4: =K4-K4*N4 -> 59 | P4: =O4-S4 -> 56.935 | Q4: =IF(L4="pending",(K4-K4*N4)-(K4-K4*N4)*R4-((K4-K4*N4)-(K4-K4*N4)*R4)*T4,0) -> 56.36565 | R4: =VLOOKUP(M4,'Payment Method'!$A$8:$B$12,2,0) -> 0.035 | S4: =O4-(O4-O4*R4) -> 2.065 | T4: 0.01 | U4: =O4-S4-((O4-S4)-(O4-S4)*T4) -> 0.56935 | V4: =IF(L4="refunded",(K4-K4*N4)-(K4-K4*N4)*R4-((K4-K4*N4)-(K4-K4*N4)*R4)*T4,0) -> 0 | W4: =IF(L4="paid",(K4-K4*N4)-(K4-K4*N4)*R4-((K4-K4*N4)-(K4-K4*N4)*R4)*T4,0) -> 0 | X4: =CHOOSE(RANDBETWEEN(1,3),"Facebook","Instagram","Tiktok") -> Instagram | Y4: =IF(COUNTIF($C$1:C3,B3)=1,10,"")
A5: 4 | B5: 46159 | C5: 46163 | D5: =TEXT(C5,"mmmm") -> May | E5: ="STU-"&RANDBETWEEN(1,1000) -> STU-531 | F5: =IF(COUNTIF($E$2:E5,E5)=1,"New Customer","Returning Customer") -> New Customer | G5: =CHOOSE(RANDBETWEEN(1,3),"Male","Female","Not specified") -> Not specified | H5: Kutaisi | I5: {=INDEX(Courses!$B$9:$B$16,RANDBETWEEN(1,8))} -> Microsoft Word | J5: =VLOOKUP(I5,Courses!$B$9:$C$16,2,0) -> Microsoft Office | K5: =VLOOKUP(I5,Courses!$B$9:$D$16,3,0) -> 29 | L5: =IF(RAND()<0.6,"Paid",IF(RAND()<0.75,"Pending","Refunded")) -> Paid | M5: {=INDEX('Payment Method'!$A$8:$A$12,RANDBETWEEN(1,5))} -> Visa Credit | N5: =IFERROR(SUMIF(Holiday!$A$8:$A$11,B5,Holiday!$C$8:$C$11),0) -> 0 | O5: =K5-K5*N5 -> 29 | P5: =O5-S5 -> 27.985 | Q5: =IF(L5="pending",(K5-K5*N5)-(K5-K5*N5)*R5-((K5-K5*N5)-(K5-K5*N5)*R5)*T5,0) -> 0 | R5: =VLOOKUP(M5,'Payment Method'!$A$8:$B$12,2,0) -> 0.035 | S5: =O5-(O5-O5*R5) -> 1.015 | T5: 0.01 | U5: =O5-S5-((O5-S5)-(O5-S5)*T5) -> 0.27985 | V5: =IF(L5="refunded",(K5-K5*N5)-(K5-K5*N5)*R5-((K5-K5*N5)-(K5-K5*N5)*R5)*T5,0) -> 0 | W5: =IF(L5="paid",(K5-K5*N5)-(K5-K5*N5)*R5-((K5-K5*N5)-(K5-K5*N5)*R5)*T5,0) -> 27.70515 | X5: =CHOOSE(RANDBETWEEN(1,3),"Facebook","Instagram","Tiktok") -> Tiktok | Y5: =IF(COUNTIF($C$1:C4,B4)=1,10,"") -> 10
A6: 5 | B6: 46031 | C6: 46035 | D6: =TEXT(C6,"mmmm") -> January | E6: ="STU-"&RANDBETWEEN(1,1000) -> STU-831 | F6: =IF(COUNTIF($E$2:E6,E6)=1,"New Customer","Returning Customer") -> New Customer | G6: =CHOOSE(RANDBETWEEN(1,3),"Male","Female","Not specified") -> Male | H6: Poti | I6: {=INDEX(Courses!$B$9:$B$16,RANDBETWEEN(1,8))} -> Tax Code | J6: =VLOOKUP(I6,Courses!$B$9:$C$16,2,0) -> Finance & Taxation | K6: =VLOOKUP(I6,Courses!$B$9:$D$16,3,0) -> 59 | L6: =IF(RAND()<0.6,"Paid",IF(RAND()<0.75,"Pending","Refunded")) -> Paid | M6: {=INDEX('Payment Method'!$A$8:$A$12,RANDBETWEEN(1,5))} -> Bank Transfer | N6: =IFERROR(SUMIF(Holiday!$A$8:$A$11,B6,Holiday!$C$8:$C$11),0) -> 0 | O6: =K6-K6*N6 -> 59 | P6: =O6-S6 -> 59 | Q6: =IF(L6="pending",(K6-K6*N6)-(K6-K6*N6)*R6-((K6-K6*N6)-(K6-K6*N6)*R6)*T6,0) -> 0 | R6: =VLOOKUP(M6,'Payment Method'!$A$8:$B$12,2,0) -> 0 | S6: =O6-(O6-O6*R6) -> 0 | T6: 0.01 | U6: =O6-S6-((O6-S6)-(O6-S6)*T6) -> 0.59 | V6: =IF(L6="refunded",(K6-K6*N6)-(K6-K6*N6)*R6-((K6-K6*N6)-(K6-K6*N6)*R6)*T6,0) -> 0 | W6: =IF(L6="paid",(K6-K6*N6)-(K6-K6*N6)*R6-((K6-K6*N6)-(K6-K6*N6)*R6)*T6,0) -> 58.41 | X6: =CHOOSE(RANDBETWEEN(1,3),"Facebook","Instagram","Tiktok") -> Tiktok | Y6: =IF(COUNTIF($C$1:C5,B5)=1,10,"")
A7: 6 | B7: 46126 | C7: 46126 | D7: =TEXT(C7,"mmmm") -> April | E7: ="STU-"&RANDBETWEEN(1,1000) -> STU-631 | F7: =IF(COUNTIF($E$2:E7,E7)=1,"New Customer","Returning Customer") -> New Customer | G7: =CHOOSE(RANDBETWEEN(1,3),"Male","Female","Not specified") -> Female | H7: Rustavi | I7: {=INDEX(Courses!$B$9:$B$16,RANDBETWEEN(1,8))} -> Excel Basics | J7: =VLOOKUP(I7,Courses!$B$9:$C$16,2,0) -> Microsoft Office | K7: =VLOOKUP(I7,Courses!$B$9:$D$16,3,0) -> 29 | L7: =IF(RAND()<0.6,"Paid",IF(RAND()<0.75,"Pending","Refunded")) -> Pending | M7: {=INDEX('Payment Method'!$A$8:$A$12,RANDBETWEEN(1,5))} -> Bank Transfer | N7: =IFERROR(SUMIF(Holiday!$A$8:$A$11,B7,Holiday!$C$8:$C$11),0) -> 0 | O7: =K7-K7*N7 -> 29 | P7: =O7-S7 -> 29 | Q7: =IF(L7="pending",(K7-K7*N7)-(K7-K7*N7)*R7-((K7-K7*N7)-(K7-K7*N7)*R7)*T7,0) -> 28.71 | R7: =VLOOKUP(M7,'Payment Method'!$A$8:$B$12,2,0) -> 0 | S7: =O7-(O7-O7*R7) -> 0 | T7: 0.01 | U7: =O7-S7-((O7-S7)-(O7-S7)*T7) -> 0.29 | V7: =IF(L7="refunded",(K7-K7*N7)-(K7-K7*N7)*R7-((K7-K7*N7)-(K7-K7*N7)*R7)*T7,0) -> 0 | W7: =IF(L7="paid",(K7-K7*N7)-(K7-K7*N7)*R7-((K7-K7*N7)-(K7-K7*N7)*R7)*T7,0) -> 0 | X7: =CHOOSE(RANDBETWEEN(1,3),"Facebook","Instagram","Tiktok") -> Tiktok | Y7: =IF(COUNTIF($C$1:C6,B6)=1,10,"")
A8: 7 | B8: 46155 | C8: 46156 | D8: =TEXT(C8,"mmmm") -> May | E8: ="STU-"&RANDBETWEEN(1,1000) -> STU-825 | F8: =IF(COUNTIF($E$2:E8,E8)=1,"New Customer","Returning Customer") -> New Customer | G8: =CHOOSE(RANDBETWEEN(1,3),"Male","Female","Not specified") -> Male | H8: Poti | I8: {=INDEX(Courses!$B$9:$B$16,RANDBETWEEN(1,8))} -> SQL | J8: =VLOOKUP(I8,Courses!$B$9:$C$16,2,0) -> Data Analytics | K8: =VLOOKUP(I8,Courses!$B$9:$D$16,3,0) -> 99 | L8: =IF(RAND()<0.6,"Paid",IF(RAND()<0.75,"Pending","Refunded")) -> Pending | M8: {=INDEX('Payment Method'!$A$8:$A$12,RANDBETWEEN(1,5))} -> Visa Credit | N8: =IFERROR(SUMIF(Holiday!$A$8:$A$11,B8,Holiday!$C$8:$C$11),0) -> 0 | O8: =K8-K8*N8 -> 99 | P8: =O8-S8 -> 95.535 | Q8: =IF(L8="pending",(K8-K8*N8)-(K8-K8*N8)*R8-((K8-K8*N8)-(K8-K8*N8)*R8)*T8,0) -> 94.57965 | R8: =VLOOKUP(M8,'Payment Method'!$A$8:$B$12,2,0) -> 0.035 | S8: =O8-(O8-O8*R8) -> 3.465 | T8: 0.01 | U8: =O8-S8-((O8-S8)-(O8-S8)*T8) -> 0.95535 | V8: =IF(L8="refunded",(K8-K8*N8)-(K8-K8*N8)*R8-((K8-K8*N8)-(K8-K8*N8)*R8)*T8,0) -> 0 | W8: =IF(L8="paid",(K8-K8*N8)-(K8-K8*N8)*R8-((K8-K8*N8)-(K8-K8*N8)*R8)*T8,0) -> 0 | X8: =CHOOSE(RANDBETWEEN(1,3),"Facebook","Instagram","Tiktok") -> Instagram | Y8: =IF(COUNTIF($C$1:C7,B7)=1,10,"") -> 10
A9: 8 | B9: 46039 | C9: 46040 | D9: =TEXT(C9,"mmmm") -> January | E9: ="STU-"&RANDBETWEEN(1,1000) -> STU-36 | F9: =IF(COUNTIF($E$2:E9,E9)=1,"New Customer","Returning Customer") -> New Customer | G9: =CHOOSE(RANDBETWEEN(1,3),"Male","Female","Not specified") -> Male | H9: Telavi | I9: {=INDEX(Courses!$B$9:$B$16,RANDBETWEEN(1,8))} -> PowerPoint | J9: =VLOOKUP(I9,Courses!$B$9:$C$16,2,0) -> Microsoft Office | K9: =VLOOKUP(I9,Courses!$B$9:$D$16,3,0) -> 29 | L9: =IF(RAND()<0.6,"Paid",IF(RAND()<0.75,"Pending","Refunded")) -> Paid | M9: {=INDEX('Payment Method'!$A$8:$A$12,RANDBETWEEN(1,5))} -> Bank Transfer | N9: =IFERROR(SUMIF(Holiday!$A$8:$A$11,B9,Holiday!$C$8:$C$11),0) -> 0 | O9: =K9-K9*N9 -> 29 | P9: =O9-S9 -> 29 | Q9: =IF(L9="pending",(K9-K9*N9)-(K9-K9*N9)*R9-((K9-K9*N9)-(K9-K9*N9)*R9)*T9,0) -> 0 | R9: =VLOOKUP(M9,'Payment Method'!$A$8:$B$12,2,0) -> 0 | S9: =O9-(O9-O9*R9) -> 0 | T9: 0.01 | U9: =O9-S9-((O9-S9)-(O9-S9)*T9) -> 0.29 | V9: =IF(L9="refunded",(K9-K9*N9)-(K9-K9*N9)*R9-((K9-K9*N9)-(K9-K9*N9)*R9)*T9,0) -> 0 | W9: =IF(L9="paid",(K9-K9*N9)-(K9-K9*N9)*R9-((K9-K9*N9)-(K9-K9*N9)*R9)*T9,0) -> 28.71 | X9: =CHOOSE(RANDBETWEEN(1,3),"Facebook","Instagram","Tiktok") -> Instagram | Y9: =IF(COUNTIF($C$1:C8,B8)=1,10,"")
A10: 9 | B10: 46178 | C10: 46180 | D10: =TEXT(C10,"mmmm") -> June | E10: ="STU-"&RANDBETWEEN(1,1000) -> STU-653 | F10: =IF(COUNTIF($E$2:E10,E10)=1,"New Customer","Returning Customer") -> New Customer | G10: =CHOOSE(RANDBETWEEN(1,3),"Male","Female","Not specified") -> Not specified | H10: Gori | I10: {=INDEX(Courses!$B$9:$B$16,RANDBETWEEN(1,8))} -> SQL | J10: =VLOOKUP(I10,Courses!$B$9:$C$16,2,0) -> Data Analytics | K10: =VLOOKUP(I10,Courses!$B$9:$D$16,3,0) -> 99 | L10: =IF(RAND()<0.6,"Paid",IF(RAND()<0.75,"Pending","Refunded")) -> Pending | M10: {=INDEX('Payment Method'!$A$8:$A$12,RANDBETWEEN(1,5))} -> Mastercard Debit | N10: =IFERROR(SUMIF(Holiday!$A$8:$A$11,B10,Holiday!$C$8:$C$11),0) -> 0 | O10: =K10-K10*N10 -> 99 | P10: =O10-S10 -> 97.02 | Q10: =IF(L10="pending",(K10-K10*N10)-(K10-K10*N10)*R10-((K10-K10*N10)-(K10-K10*N10)*R10)*T10,0) -> 96.0498 | R10: =VLOOKUP(M10,'Payment Method'!$A$8:$B$12,2,0) -> 0.02 | S10: =O10-(O10-O10*R10) -> 1.98 | T10: 0.01 | U10: =O10-S10-((O10-S10)-(O10-S10)*T10) -> 0.9702 | V10: =IF(L10="refunded",(K10-K10*N10)-(K10-K10*N10)*R10-((K10-K10*N10)-(K10-K10*N10)*R10)*T10,0) -> 0 | W10: =IF(L10="paid",(K10-K10*N10)-(K10-K10*N10)*R10-((K10-K10*N10)-(K10-K10*N10)*R10)*T10,0) -> 0 | X10: =CHOOSE(RANDBETWEEN(1,3),"Facebook","Instagram","Tiktok") -> Facebook | Y10: =IF(COUNTIF($C$1:C9,B9)=1,10,"")
A11: 10 | B11: 46037 | C11: 46042 | D11: =TEXT(C11,"mmmm") -> January | E11: ="STU-"&RANDBETWEEN(1,1000) -> STU-8 | F11: =IF(COUNTIF($E$2:E11,E11)=1,"New Customer","Returning Customer") -> New Customer | G11: =CHOOSE(RANDBETWEEN(1,3),"Male","Female","Not specified") -> Male | H11: Batumi | I11: {=INDEX(Courses!$B$9:$B$16,RANDBETWEEN(1,8))} -> Complete Excel Course | J11: =VLOOKUP(I11,Courses!$B$9:$C$16,2,0) -> Microsoft Office | K11: =VLOOKUP(I11,Courses!$B$9:$D$16,3,0) -> 59 | L11: =IF(RAND()<0.6,"Paid",IF(RAND()<0.75,"Pending","Refunded")) -> Paid | M11: {=INDEX('Payment Method'!$A$8:$A$12,RANDBETWEEN(1,5))} -> Visa Debit | N11: =IFERROR(SUMIF(Holiday!$A$8:$A$11,B11,Holiday!$C$8:$C$11),0) -> 0 | O11: =K11-K11*N11 -> 59 | P11: =O11-S11 -> 57.82 | Q11: =IF(L11="pending",(K11-K11*N11)-(K11-K11*N11)*R11-((K11-K11*N11)-(K11-K11*N11)*R11)*T11,0) -> 0 | R11: =VLOOKUP(M11,'Payment Method'!$A$8:$B$12,2,0) -> 0.02 | S11: =O11-(O11-O11*R11) -> 1.18 | T11: 0.01 | U11: =O11-S11-((O11-S11)-(O11-S11)*T11) -> 0.5782 | V11: =IF(L11="refunded",(K11-K11*N11)-(K11-K11*N11)*R11-((K11-K11*N11)-(K11-K11*N11)*R11)*T11,0) -> 0 | W11: =IF(L11="paid",(K11-K11*N11)-(K11-K11*N11)*R11-((K11-K11*N11)-(K11-K11*N11)*R11)*T11,0) -> 57.2418 | X11: =CHOOSE(RANDBETWEEN(1,3),"Facebook","Instagram","Tiktok") -> Instagram | Y11: =IF(COUNTIF($C$1:C10,B10)=1,10,"")
A12: 11 | B12: 46228 | C12: 46231 | D12: =TEXT(C12,"mmmm") -> July | E12: ="STU-"&RANDBETWEEN(1,1000) -> STU-930 | F12: =IF(COUNTIF($E$2:E12,E12)=1,"New Customer","Returning Customer") -> New Customer | G12: =CHOOSE(RANDBETWEEN(1,3),"Male","Female","Not specified") -> Female | H12: Kutaisi | I12: {=INDEX(Courses!$B$9:$B$16,RANDBETWEEN(1,8))} -> Adolescent Psychology | J12: =VLOOKUP(I12,Courses!$B$9:$C$16,2,0) -> Psychology | K12: =VLOOKUP(I12,Courses!$B$9:$D$16,3,0) -> 29 | L12: =IF(RAND()<0.6,"Paid",IF(RAND()<0.75,"Pending","Refunded")) -> Paid | M12: {=INDEX('Payment Method'!$A$8:$A$12,RANDBETWEEN(1,5))} -> Mastercard Credit | N12: =IFERROR(SUMIF(Holiday!$A$8:$A$11,B12,Holiday!$C$8:$C$11),0) -> 0 | O12: =K12-K12*N12 -> 29 | P12: =O12-S12 -> 27.985 | Q12: =IF(L12="pending",(K12-K12*N12)-(K12-K12*N12)*R12-((K12-K12*N12)-(K12-K12*N12)*R12)*T12,0) -> 0 | R12: =VLOOKUP(M12,'Payment Method'!$A$8:$B$12,2,0) -> 0.035 | S12: =O12-(O12-O12*R12) -> 1.015 | T12: 0.01 | U12: =O12-S12-((O12-S12)-(O12-S12)*T12) -> 0.27985 | V12: =IF(L12="refunded",(K12-K12*N12)-(K12-K12*N12)*R12-((K12-K12*N12)-(K12-K12*N12)*R12)*T12,0) -> 0 | W12: =IF(L12="paid",(K12-K12*N12)-(K12-K12*N12)*R12-((K12-K12*N12)-(K12-K12*N12)*R12)*T12,0) -> 27.70515 | X12: =CHOOSE(RANDBETWEEN(1,3),"Facebook","Instagram","Tiktok") -> Tiktok | Y12: =IF(COUNTIF($C$1:C11,B11)=1,10,"")
A13: 12 | B13: 46116 | C13: 46116 | D13: =TEXT(C13,"mmmm") -> April | E13: ="STU-"&RANDBETWEEN(1,1000) -> STU-994 | F13: =IF(COUNTIF($E$2:E13,E13)=1,"New Customer","Returning Customer") -> New Customer | G13: =CHOOSE(RANDBETWEEN(1,3),"Male","Female","Not specified") -> Female | H13: Poti | I13: {=INDEX(Courses!$B$9:$B$16,RANDBETWEEN(1,8))} -> Complete Excel Course | J13: =VLOOKUP(I13,Courses!$B$9:$C$16,2,0) -> Microsoft Office | K13: =VLOOKUP(I13,Courses!$B$9:$D$16,3,0) -> 59 | L13: =IF(RAND()<0.6,"Paid",IF(RAND()<0.75,"Pending","Refunded")) -> Pending | M13: {=INDEX('Payment Method'!$A$8:$A$12,RANDBETWEEN(1,5))} -> Mastercard Credit | N13: =IFERROR(SUMIF(Holiday!$A$8:$A$11,B13,Holiday!$C$8:$C$11),0) -> 0 | O13: =K13-K13*N13 -> 59 | P13: =O13-S13 -> 56.935 | Q13: =IF(L13="pending",(K13-K13*N13)-(K13-K13*N13)*R13-((K13-K13*N13)-(K13-K13*N13)*R13)*T13,0) -> 56.36565 | R13: =VLOOKUP(M13,'Payment Method'!$A$8:$B$12,2,0) -> 0.035 | S13: =O13-(O13-O13*R13) -> 2.065 | T13: 0.01 | U13: =O13-S13-((O13-S13)-(O13-S13)*T13) -> 0.56935 | V13: =IF(L13="refunded",(K13-K13*N13)-(K13-K13*N13)*R13-((K13-K13*N13)-(K13-K13*N13)*R13)*T13,0) -> 0 | W13: =IF(L13="paid",(K13-K13*N13)-(K13-K13*N13)*R13-((K13-K13*N13)-(K13-K13*N13)*R13)*T13,0) -> 0 | X13: =CHOOSE(RANDBETWEEN(1,3),"Facebook","Instagram","Tiktok") -> Facebook | Y13: =IF(COUNTIF($C$1:C12,B12)=1,10,"")
A14: 13 | B14: 46179 | C14: 46181 | D14: =TEXT(C14,"mmmm") -> June | E14: ="STU-"&RANDBETWEEN(1,1000) -> STU-220 | F14: =IF(COUNTIF($E$2:E14,E14)=1,"New Customer","Returning Customer") -> New Customer | G14: =CHOOSE(RANDBETWEEN(1,3),"Male","Female","Not specified") -> Female | H14: Kutaisi | I14: {=INDEX(Courses!$B$9:$B$16,RANDBETWEEN(1,8))} -> Excel Basics | J14: =VLOOKUP(I14,Courses!$B$9:$C$16,2,0) -> Microsoft Office | K14: =VLOOKUP(I14,Courses!$B$9:$D$16,3,0) -> 29 | L14: =IF(RAND()<0.6,"Paid",IF(RAND()<0.75,"Pending","Refunded")) -> Paid | M14: {=INDEX('Payment Method'!$A$8:$A$12,RANDBETWEEN(1,5))} -> Mastercard Debit | N14: =IFERROR(SUMIF(Holiday!$A$8:$A$11,B14,Holiday!$C$8:$C$11),0) -> 0 | O14: =K14-K14*N14 -> 29 | P14: =O14-S14 -> 28.42 | Q14: =IF(L14="pending",(K14-K14*N14)-(K14-K14*N14)*R14-((K14-K14*N14)-(K14-K14*N14)*R14)*T14,0) -> 0 | R14: =VLOOKUP(M14,'Payment Method'!$A$8:$B$12,2,0) -> 0.02 | S14: =O14-(O14-O14*R14) -> 0.58 | T14: 0.01 | U14: =O14-S14-((O14-S14)-(O14-S14)*T14) -> 0.2842 | V14: =IF(L14="refunded",(K14-K14*N14)-(K14-K14*N14)*R14-((K14-K14*N14)-(K14-K14*N14)*R14)*T14,0) -> 0 | W14: =IF(L14="paid",(K14-K14*N14)-(K14-K14*N14)*R14-((K14-K14*N14)-(K14-K14*N14)*R14)*T14,0) -> 28.1358 | X14: =CHOOSE(RANDBETWEEN(1,3),"Facebook","Instagram","Tiktok") -> Instagram | Y14: =IF(COUNTIF($C$1:C13,B13)=1,10,"") -> 10
... A1001: 1000 | B1001: 46104 | C1001: 46104 | D1001: =TEXT(C1001,"mmmm") -> March | E1001: ="STU-"&RANDBETWEEN(1,1000) -> STU-267 | F1001: =IF(COUNTIF($E$2:E1001,E1001)=1,"New Customer","Returning Customer") -> New Customer | G1001: =CHOOSE(RANDBETWEEN(1,3),"Male","Female","Not specified") -> Female | H1001: Batumi | I1001: {=INDEX(Courses!$B$9:$B$16,RANDBETWEEN(1,8))} -> Adolescent Psychology | J1001: =VLOOKUP(I1001,Courses!$B$9:$C$16,2,0) -> Psychology | K1001: =VLOOKUP(I1001,Courses!$B$9:$D$16,3,0) -> 29 | L1001: =IF(RAND()<0.6,"Paid",IF(RAND()<0.75,"Pending","Refunded")) -> Paid | M1001: {=INDEX('Payment Method'!$A$8:$A$12,RANDBETWEEN(1,5))} -> Mastercard Credit | N1001: =IFERROR(SUMIF(Holiday!$A$8:$A$11,B1001,Holiday!$C$8:$C$11),0) -> 0 | O1001: =K1001-K1001*N1001 -> 29 | P1001: =O1001-S1001 -> 27.985 | Q1001: =IF(L1001="pending",(K1001-K1001*N1001)-(K1001-K1001*N1001)*R1001-((K1001-K1001*N1001)-(K1001-K1001*N1001)*R1001)*T1001,0) -> 0 | R1001: =VLOOKUP(M1001,'Payment Method'!$A$8:$B$12,2,0) -> 0.035 | S1001: =O1001-(O1001-O1001*R1001) -> 1.015 | T1001: 0.01 | U1001: =O1001-S1001-((O1001-S1001)-(O1001-S1001)*T1001) -> 0.27985 | V1001: =IF(L1001="refunded",(K1001-K1001*N1001)-(K1001-K1001*N1001)*R1001-((K1001-K1001*N1001)-(K1001-K1001*N1001)*R1001)*T1001,0) -> 0 | W1001: =IF(L1001="paid",(K1001-K1001*N1001)-(K1001-K1001*N1001)*R1001-((K1001-K1001*N1001)-(K1001-K1001*N1001)*R1001)*T1001,0) -> 27.70515 | X1001: =CHOOSE(RANDBETWEEN(1,3),"Facebook","Instagram","Tiktok") -> Tiktok | Y1001: =IF(COUNTIF($C$1:C1000,B1000)=1,10,"")

Sheet Dashboard
A1: Kursebi.Online Sales Dashboard
A12: Interactive Sales Dashboard | Jan–Jul 2026
A20: Key Performance Indicators
AK34: Distribution Analysis
A45: Dashboard Filters
A78: Sales Performance

Sheet Analysis
A1: 1.Sales Overview | D1: 2.Monthly Sales Analysis | I1: 4. Marketing Analysis | O1: 6.Customer Analysis
A2: Metric | B2: Value | D2: Month | E2: Sales Count | F2: Total sales | G2: Net Revenue | I2: Marketing Channel | J2: Sales | K2: Total sales | L2: Ad Spend | M2: ROAS | O2: Customer Type | P2: Customers | Q2: Total Sales
A3: Total Sales | B3: =SUM(totalsales) -> 39502.975 | D3: January | E3: =COUNTIF(PAYMENTm,"JANUARY") -> 152 | F3: =SUMIF(PAYMENTm,D3,totalsales) -> 2974.48 | G3: =SUMIF(PAYMENTm,D3,netrevenue) -> 3240.666 | I3: Facebook | J3: =COUNTA(Course) -> 1000 | K3: =SUM(totalsales) -> 39502.975 | L3: =SUM(adspend) -> 2100 | M3: =K3/L3 -> 18.81094 | O3: New Customer | P3: =COUNTIF(customertype,O3) -> 635 | Q3: =SUMIF(customertype,O3,totalsales) -> 24695.185
A4: Expected Revenue | B4: =SUM(expectedrevenue) -> 10155.683 | D4: February | E4: =COUNTIF(PAYMENTm,"FEBRUARY") -> 128 | F4: =SUMIF(PAYMENTm,D4,totalsales) -> 6639.905 | G4: =SUMIF(PAYMENTm,D4,netrevenue) -> 3741.4872 | I4: Instagram | O4: Returning Customer | P4: =COUNTIF('Sales Data'!$F$2:$F$1001,"Returning Customer") -> 365 | Q4: =SUMIF(customertype,O4,totalsales) -> 14807.79
A5: Net Revenue | B5: =SUM(netrevenue) -> 24671.077 | D5: March | E5: =COUNTIF(PAYMENTm,"MARCH") -> 145 | F5: =SUMIF(PAYMENTm,D5,totalsales) -> 1981.915 | G5: =SUMIF(PAYMENTm,D5,netrevenue) -> 779.1993 | I5: Tiktok | O5: TOTAL | P5: =SUM(P3:P4) -> 1000 | Q5: =SUM(Q3:Q4) -> 39502.975
A6: Total Unique Students | B6: =COUNTIF(customertype,"new customer") -> 635 | D6: April | E6: =COUNTIF(PAYMENTm,"APRIL") -> 141 | F6: =SUMIF(PAYMENTm,D6,totalsales) -> 6871.81 | G6: =SUMIF(PAYMENTm,D6,netrevenue) -> 3705.07
A7: Total Discounts | B7: =SUM(discountamount) -> 280 | D7: May | E7: =COUNTIF(PAYMENTm,"MAY") -> 146 | F7: =SUMIF(PAYMENTm,D7,totalsales) -> 7079.445 | G7: =SUMIF(PAYMENTm,D7,netrevenue) -> 4822.5177 | I7: 5.Payment Analysis | O7: 7.City Analysis
A8: Total Bank Fees | B8: =SUM(bankcommisionamount) -> 927.025 | D8: June | E8: =COUNTIF(PAYMENTm,"JUNE") -> 132 | F8: =SUMIF(PAYMENTm,D8,totalsales) -> 6715.61 | G8: =SUMIF(PAYMENTm,D8,netrevenue) -> 4277.7504 | I8: Payment Status | J8: Number of Orders | K8: Amount | O8: City | P8: Number of Students | Q8: Total Sales
A9: Total Tax Fees | B9: =SUM(incometaxamount) -> 395.02975 | D9: July | E9: =COUNTIF(PAYMENTm,"JULY") -> 156 | F9: =SUMIF(PAYMENTm,D9,totalsales) -> 7239.81 | G9: =SUMIF(PAYMENTm,D9,netrevenue) -> 4104.3865 | I9: Paid | J9: =COUNTIF(paymentstatus,I9) -> 633 | K9: =SUMIF(paymentstatus,I9,totalsales) -> 24920.28 | O9: Gori | P9: =COUNTIF(City,O9) -> 155 | Q9: =SUMIF(City,O9,totalsales) -> 5460.26
A10: Total Ad Spend | B10: =SUM(adspend) -> 2100 | D10: TOTAL | E10: =SUM(E3:E9) -> 1000 | F10: =SUM(F3:F9) -> 39502.975 | G10: =SUM(G3:G9) -> 24671.077 | I10: Pending | J10: =COUNTIF(paymentstatus,I10) -> 278 | K10: =SUMIF(paymentstatus,I10,totalsales) -> 10257.67 | O10: Batumi | P10: =COUNTIF(City,O10) -> 111 | Q10: =SUMIF(City,O10,totalsales) -> 5098.625
A11: Other charges | B11: 80 | I11: Refunded | J11: =COUNTIF(paymentstatus,I11) -> 89 | K11: =SUMIF(paymentstatus,I11,totalsales) -> 4325.025 | O11: Kutaisi | P11: =COUNTIF(City,O11) -> 135 | Q11: =SUMIF(City,O11,totalsales) -> 5166.375
A12: Profit | B12: =B5-B10-B11 -> 22491.077 | D12: 3.Course Performance | I12: TOTAL | J12: =SUM(J9:J11) -> 1000 | K12: =SUM(K9:K11) -> 39502.975 | O12: Poti | P12: =COUNTIF(City,O12) -> 123 | Q12: =SUMIF(City,O12,totalsales) -> 4291.28
A13: Profit Margin % | B13: =B12/B5*100 -> 91.163742 | D13: Course | E13: Number of Sales | F13: Total sales | G13: Net Revenue | O13: Rustavi | P13: =COUNTIF(City,O13) -> 116 | Q13: =SUMIF(City,O13,totalsales) -> 4241.73
A14: Average Revenue per Student | B14: =B3/B6 -> 62.209409 | D14: Tax Code | E14: =COUNTIF(Course,D14) -> 124 | F14: =SUMIF(Course,D14,totalsales) -> 6000.005 | G14: =SUMIF(Course,D14,netrevenue) -> 2940.3049 | O14: Telavi | P14: =COUNTIF(City,O14) -> 114 | Q14: =SUMIF(City,O14,totalsales) -> 4258.425
D15: Excel Basics | E15: =COUNTIF(Course,D15) -> 115 | F15: =SUMIF(Course,D15,totalsales) -> 1544.975 | G15: =SUMIF(Course,D15,netrevenue) -> 2267.496 | O15: Zugdidi | P15: =COUNTIF(City,O15) -> 115 | Q15: =SUMIF(City,O15,totalsales) -> 5209.855
D16: Complete Excel Course | E16: =COUNTIF(Course,D16) -> 124 | F16: =SUMIF(Course,D16,totalsales) -> 6009.15 | G16: =SUMIF(Course,D16,netrevenue) -> 4042.2343 | O16: Tbilisi | P16: =COUNTIF(City,O16) -> 131 | Q16: =SUMIF(City,O16,totalsales) -> 5776.425
D17: Power BI | E17: =COUNTIF(Course,D17) -> 137 | F17: =SUMIF(Course,D17,totalsales) -> 6747.83 | G17: =SUMIF(Course,D17,netrevenue) -> 3303.9319 | O17: TOTAL | P17: =SUM(P15:P16) -> 246 | Q17: =SUM(Q15:Q16) -> 10986.28
D18: SQL | E18: =COUNTIF(Course,D18) -> 140 | F18: =SUMIF(Course,D18,totalsales) -> 13572.405 | G18: =SUMIF(Course,D18,netrevenue) -> 4351.0153
D19: Microsoft Word | E19: =COUNTIF(Course,D19) -> 129 | F19: =SUMIF(Course,D19,totalsales) -> 3654.87 | G19: =SUMIF(Course,D19,netrevenue) -> 2912.6691
D20: PowerPoint | E20: =COUNTIF(Course,D20) -> 112 | F20: =SUMIF(Course,D20,totalsales) -> 1436.225 | G20: =SUMIF(Course,D20,netrevenue) -> 2616.1047
D21: Adolescent Psychology | E21: =COUNTIF(Course,D21) -> 119 | F21: =SUMIF(Course,D21,totalsales) -> 537.515 | G21: =SUMIF(Course,D21,netrevenue) -> 2237.3208
D22: TOTAL | E22: =SUM(E14:E21) -> 1000 | F22: =SUM(F14:F21) -> 39502.975 | G22: =SUM(G14:G21) -> 24671.077

Sheet KPI Summary
A8: Metric | B8: Value
A9: Total Sales | B9: =SUM(totalsales) -> 39502.975
A10: Expected Revenue | B10: =SUM(expectedrevenue) -> 10155.683
A11: Refund Amount | B11: =SUM(refundamount) -> 4281.7747
A12: Total Unique Students | B12: =COUNTIF(customertype,"New Customer") -> 635
A13: Total Saled Course | B13: =COUNTA(Course) -> 1000
A14: Total Discounts | B14: =SUM(discountamount) -> 280
A15: Total Bank Fees | B15: =SUM(bankcommisionamount) -> 927.025
A16: Tax fees | B16: =SUM(incometaxamount) -> 395.02975
A17: Total Ads fees | B17: =SUM(adspend) -> 2100

Sheet Payment Method
A7: Payment_Method | B7: Fee
A8: Visa Debit | B8: 0.02
A9: Mastercard Debit | B9: 0.02
A10: Visa Credit | B10: 0.035
A11: Mastercard Credit | B11: 0.035
A12: Bank Transfer | B12: 0

Sheet Holiday
A7: Date | B7: Holiday | C7: Discount
A8: 46023 | B8: New Year | C8: 20
A9: 46084 | B9: Mother's Day | C9: 20
A10: 46360 | B10: Easter | C10: 10
A11: 26/05/2026 | B11: Independence Day | C11: 20

Sheet Courses
A8: Course_ID | B8: Course_Name | C8: Category | D8: Price
A9: CRS001 | B9: Tax Code | C9: Finance & Taxation | D9: 59
A10: CRS002 | B10: Excel Basics | C10: Microsoft Office | D10: 29
A11: CRS003 | B11: Complete Excel Course | C11: Microsoft Office | D11: 59
A12: CRS004 | B12: Power BI | C12: Data Analytics | D12: 59
A13: CRS005 | B13: SQL | C13: Data Analytics | D13: 99
A14: CRS006 | B14: Microsoft Word | C14: Microsoft Office | D14: 29
A15: CRS007 | B15: PowerPoint | C15: Microsoft Office | D15: 29
A16: CRS008 | B16: Adolescent Psychology | C16: Psychology | D16: 29
